retclient/__init__.py
retclient/client.py
retclient-0.1.5.dist-info/LICENSE
retclient-0.1.5.dist-info/WHEEL
retclient-0.1.5.dist-info/METADATA
retclient-0.1.5.dist-info/RECORD
