Metadata-Version: 2.1
Name: retclient
Version: 0.1.5
Summary: A client package for RetinaFace.
Home-page: https://github.com/reeve0930/pyzaim
License: MIT
Keywords: face detection,Retina Face
Author: reeve0930
Author-email: reeve0930@gmail.com
Requires-Python: >=3.7,<4.0
Classifier: License :: OSI Approved :: MIT License
Classifier: Programming Language :: Python :: 3
Classifier: Programming Language :: Python :: 3.7
Classifier: Programming Language :: Python :: 3.8
Classifier: Programming Language :: Python :: 3.9
Requires-Dist: numpy (>=1.19.2,<2.0.0)
Requires-Dist: opencv-python (>=4.4.0,<5.0.0)
Requires-Dist: reelib (>=1.4.1,<2.0.0)
Requires-Dist: requests (>=2.24.0,<3.0.0)
Project-URL: Repository, https://github.com/reeve0930/pyzaim
